[
  {
    "id": "high-roller",
    "name": "🎲 High Roller",
    "luck": 0.1
  },
  {
    "id": "ultra-roller",
    "name": "🎲 Ultra Roller",
    "luck": 0.2
  },
  {
    "id": "secret-hunter",
    "name": "🔮 Secret Hunter",
    "secretLuck": 0.05
  },
  {
    "id": "shiny-seeker",
    "name": "🌟 Shiny seeker",
    "shinyChance": 0.01
  },
  {
    "id": "burst-blessing",
    "name": "🥚 Burst Blessing",
    "super": true
  },
  {
    "id": "luck-boost",
    "name": "🍀 Luck Boost",
    "luckMultiplier": 1,
    "super": true
  },
  {
    "id": "hatch-blessing",
    "name": "⚡ Hatch Blessing",
    "baseHatchSpeed": 0.75,
    "super": true
  },
  {
    "id": "shiny-blessing",
    "name": "🌟 Shiny Blessing",
    "shinyChance": 0.05,
    "super": true
  },
  {
    "id": "mythic-blessing",
    "name": "🔮 Mythic Blessing",
    "mythicChance": 0.05,
    "super": true
  },
  {
    "id": "infinity-blessing",
    "name": "♾️ Infinity Blessing",
    "infinityLuck": 0.025,
    "super": true
  }
]
